{
"meta":{"test_sets":[],"test_metrics":[],"learn_metrics":[{"best_value":"Min","name":"Logloss"}],"launch_mode":"Train","parameters":"","iteration_count":415,"learn_sets":["learn"],"name":"experiment"},
"iterations":[
{"learn":[0.6730274857],"iteration":0,"passed_time":0.05216266678,"remaining_time":21.59534405},
{"learn":[0.6535728438],"iteration":1,"passed_time":0.1008304766,"remaining_time":20.82149341},
{"learn":[0.6341176954],"iteration":2,"passed_time":0.158794004,"remaining_time":21.80770988},
{"learn":[0.6207456432],"iteration":3,"passed_time":0.2176688111,"remaining_time":22.36547034},
{"learn":[0.6084975218],"iteration":4,"passed_time":0.2770485897,"remaining_time":22.71798435},
{"learn":[0.5963581875],"iteration":5,"passed_time":0.3453548295,"remaining_time":23.54168754},
{"learn":[0.5890532806],"iteration":6,"passed_time":0.4062821443,"remaining_time":23.68044498},
{"learn":[0.5844478105],"iteration":7,"passed_time":0.4411828272,"remaining_time":22.44517633},
{"learn":[0.5784902004],"iteration":8,"passed_time":0.4994826031,"remaining_time":22.53221521},
{"learn":[0.5736677803],"iteration":9,"passed_time":0.5433594452,"remaining_time":22.00605753},
{"learn":[0.5689662127],"iteration":10,"passed_time":0.5989747479,"remaining_time":21.99870892},
{"learn":[0.5648948874],"iteration":11,"passed_time":0.6613412926,"remaining_time":22.21004508},
{"learn":[0.5604419941],"iteration":12,"passed_time":0.7328298608,"remaining_time":22.66135416},
{"learn":[0.5562253704],"iteration":13,"passed_time":0.7946600045,"remaining_time":22.76133298},
{"learn":[0.5515682414],"iteration":14,"passed_time":0.8615190268,"remaining_time":22.97384071},
{"learn":[0.5466154809],"iteration":15,"passed_time":0.9337762606,"remaining_time":23.2860455},
{"learn":[0.5436351586],"iteration":16,"passed_time":0.9955431288,"remaining_time":23.30742149},
{"learn":[0.5411597399],"iteration":17,"passed_time":1.071597679,"remaining_time":23.63468215},
{"learn":[0.537845463],"iteration":18,"passed_time":1.131903489,"remaining_time":23.59125167},
{"learn":[0.5348944011],"iteration":19,"passed_time":1.204024808,"remaining_time":23.77948995},
{"learn":[0.5326302555],"iteration":20,"passed_time":1.263945086,"remaining_time":23.71401734},
{"learn":[0.5307537273],"iteration":21,"passed_time":1.326155997,"remaining_time":23.68996849},
{"learn":[0.5285164092],"iteration":22,"passed_time":1.393061323,"remaining_time":23.74261037},
{"learn":[0.5266245484],"iteration":23,"passed_time":1.457239038,"remaining_time":23.74085267},
{"learn":[0.5245966329],"iteration":24,"passed_time":1.513533993,"remaining_time":23.61113029},
{"learn":[0.5240433526],"iteration":25,"passed_time":1.541804242,"remaining_time":23.06776346},
{"learn":[0.5226544106],"iteration":26,"passed_time":1.597527435,"remaining_time":22.95706092},
{"learn":[0.5210544128],"iteration":27,"passed_time":1.655427432,"remaining_time":22.880372},
{"learn":[0.5202476533],"iteration":28,"passed_time":1.721737324,"remaining_time":22.91691748},
{"learn":[0.5190106596],"iteration":29,"passed_time":1.784703643,"remaining_time":22.90369675},
{"learn":[0.5178617669],"iteration":30,"passed_time":1.842016357,"remaining_time":22.81723487},
{"learn":[0.5166857962],"iteration":31,"passed_time":1.902967574,"remaining_time":22.77614315},
{"learn":[0.5160026549],"iteration":32,"passed_time":1.979651066,"remaining_time":22.91596082},
{"learn":[0.5154694231],"iteration":33,"passed_time":2.037310514,"remaining_time":22.82986193},
{"learn":[0.515056608],"iteration":34,"passed_time":2.093218092,"remaining_time":22.72636786},
{"learn":[0.5145425592],"iteration":35,"passed_time":2.150293013,"remaining_time":22.637807},
{"learn":[0.5134857306],"iteration":36,"passed_time":2.214063147,"remaining_time":22.61934783},
{"learn":[0.512687669],"iteration":37,"passed_time":2.270857342,"remaining_time":22.52929521},
{"learn":[0.5121618728],"iteration":38,"passed_time":2.329705197,"remaining_time":22.46074754},
{"learn":[0.5114653153],"iteration":39,"passed_time":2.391289193,"remaining_time":22.41833618},
{"learn":[0.5113035436],"iteration":40,"passed_time":2.422777414,"remaining_time":22.10045739},
{"learn":[0.5106963954],"iteration":41,"passed_time":2.488128229,"remaining_time":22.09694832},
{"learn":[0.5103131697],"iteration":42,"passed_time":2.545834109,"remaining_time":22.02442532},
{"learn":[0.510267021],"iteration":43,"passed_time":2.569096062,"remaining_time":21.66215089},
{"learn":[0.509797511],"iteration":44,"passed_time":2.62995066,"remaining_time":21.62403876},
{"learn":[0.508780551],"iteration":45,"passed_time":2.691774079,"remaining_time":21.59270946},
{"learn":[0.5081971266],"iteration":46,"passed_time":2.752057952,"remaining_time":21.54802822},
{"learn":[0.5078506494],"iteration":47,"passed_time":2.819070888,"remaining_time":21.55414617},
{"learn":[0.5070478205],"iteration":48,"passed_time":2.880540724,"remaining_time":21.51587561},
{"learn":[0.5066911025],"iteration":49,"passed_time":2.944765979,"remaining_time":21.49679165},
{"learn":[0.5061058498],"iteration":50,"passed_time":3.009373746,"remaining_time":21.47866752},
{"learn":[0.5057525585],"iteration":51,"passed_time":3.082316889,"remaining_time":21.5169429},
{"learn":[0.5057129673],"iteration":52,"passed_time":3.121951747,"remaining_time":21.32351948},
{"learn":[0.5054575968],"iteration":53,"passed_time":3.184185613,"remaining_time":21.28687049},
{"learn":[0.5050026066],"iteration":54,"passed_time":3.24555273,"remaining_time":21.24361787},
{"learn":[0.5045637737],"iteration":55,"passed_time":3.299667558,"remaining_time":21.15322595},
{"learn":[0.5041299812],"iteration":56,"passed_time":3.380796536,"remaining_time":21.23377474},
{"learn":[0.5037051566],"iteration":57,"passed_time":3.436860228,"remaining_time":21.15446727},
{"learn":[0.5031834646],"iteration":58,"passed_time":3.497680455,"remaining_time":21.10464817},
{"learn":[0.5029825185],"iteration":59,"passed_time":3.562342859,"remaining_time":21.07719525},
{"learn":[0.5026228477],"iteration":60,"passed_time":3.626789768,"remaining_time":21.04727177},
{"learn":[0.5024118941],"iteration":61,"passed_time":3.690242826,"remaining_time":21.01057609},
{"learn":[0.50188517],"iteration":62,"passed_time":3.751693084,"remaining_time":20.96184073},
{"learn":[0.5018828498],"iteration":63,"passed_time":3.773866457,"remaining_time":20.69729885},
{"learn":[0.5015006198],"iteration":64,"passed_time":3.834614161,"remaining_time":20.6479224},
{"learn":[0.5009225348],"iteration":65,"passed_time":3.893995937,"remaining_time":20.59097852},
{"learn":[0.5006303318],"iteration":66,"passed_time":3.954264722,"remaining_time":20.538569},
{"learn":[0.500129527],"iteration":67,"passed_time":4.022808849,"remaining_time":20.52815692},
{"learn":[0.5000035122],"iteration":68,"passed_time":4.083909,"remaining_time":20.47873209},
{"learn":[0.4996926693],"iteration":69,"passed_time":4.146063033,"remaining_time":20.43416781},
{"learn":[0.4993712946],"iteration":70,"passed_time":4.209683131,"remaining_time":20.39621123},
{"learn":[0.4991004388],"iteration":71,"passed_time":4.270194487,"remaining_time":20.34273207},
{"learn":[0.4989188346],"iteration":72,"passed_time":4.325543143,"remaining_time":20.26487335},
{"learn":[0.4986981222],"iteration":73,"passed_time":4.394731403,"remaining_time":20.25139741},
{"learn":[0.4984975439],"iteration":74,"passed_time":4.47871801,"remaining_time":20.30352164},
{"learn":[0.4981394013],"iteration":75,"passed_time":4.534653962,"remaining_time":20.22694333},
{"learn":[0.4979756108],"iteration":76,"passed_time":4.59091329,"remaining_time":20.15232068},
{"learn":[0.4978088592],"iteration":77,"passed_time":4.650225185,"remaining_time":20.09135753},
{"learn":[0.4977563847],"iteration":78,"passed_time":4.711602287,"remaining_time":20.03921985},
{"learn":[0.4976574193],"iteration":79,"passed_time":4.742962973,"remaining_time":19.86115745},
{"learn":[0.4976214399],"iteration":80,"passed_time":4.803964496,"remaining_time":19.80894002},
{"learn":[0.4976214199],"iteration":81,"passed_time":4.831171839,"remaining_time":19.61927101},
{"learn":[0.4975313595],"iteration":82,"passed_time":4.894847422,"remaining_time":19.57938969},
{"learn":[0.4972411781],"iteration":83,"passed_time":4.966218996,"remaining_time":19.56926771},
{"learn":[0.4971643881],"iteration":84,"passed_time":5.044915352,"remaining_time":19.58614196},
{"learn":[0.4970830555],"iteration":85,"passed_time":5.119986747,"remaining_time":19.58692604},
{"learn":[0.4967167347],"iteration":86,"passed_time":5.191597056,"remaining_time":19.57291764},
{"learn":[0.4966633894],"iteration":87,"passed_time":5.257651067,"remaining_time":19.5369534},
{"learn":[0.4966546696],"iteration":88,"passed_time":5.303180329,"remaining_time":19.42513244},
{"learn":[0.4962957499],"iteration":89,"passed_time":5.371585648,"remaining_time":19.39739262},
{"learn":[0.4960553822],"iteration":90,"passed_time":5.435177128,"remaining_time":19.35161967},
{"learn":[0.4959397771],"iteration":91,"passed_time":5.507979806,"remaining_time":19.33779867},
{"learn":[0.4956729764],"iteration":92,"passed_time":5.564711739,"remaining_time":19.26706645},
{"learn":[0.494939791],"iteration":93,"passed_time":5.630646325,"remaining_time":19.22805819},
{"learn":[0.4946572071],"iteration":94,"passed_time":5.695741206,"remaining_time":19.18565459},
{"learn":[0.4944636937],"iteration":95,"passed_time":5.765538223,"remaining_time":19.15840305},
{"learn":[0.4944519951],"iteration":96,"passed_time":5.805144416,"remaining_time":19.03129819},
{"learn":[0.4939150539],"iteration":97,"passed_time":5.87807564,"remaining_time":19.01377529},
{"learn":[0.4935753123],"iteration":98,"passed_time":5.938519306,"remaining_time":18.95527375},
{"learn":[0.493148572],"iteration":99,"passed_time":6.002864633,"remaining_time":18.90902359},
{"learn":[0.4930767476],"iteration":100,"passed_time":6.066855912,"remaining_time":18.86131442},
{"learn":[0.4928507012],"iteration":101,"passed_time":6.134409763,"remaining_time":18.8242182},
{"learn":[0.4927276941],"iteration":102,"passed_time":6.197909622,"remaining_time":18.77425051},
{"learn":[0.4926707231],"iteration":103,"passed_time":6.237247503,"remaining_time":18.65176898},
{"learn":[0.4925146511],"iteration":104,"passed_time":6.31711253,"remaining_time":18.65052271},
{"learn":[0.4924140803],"iteration":105,"passed_time":6.384513128,"remaining_time":18.61145808},
{"learn":[0.4924137754],"iteration":106,"passed_time":6.415873506,"remaining_time":18.46812187},
{"learn":[0.4923212224],"iteration":107,"passed_time":6.481501965,"remaining_time":18.42426947},
{"learn":[0.4921828641],"iteration":108,"passed_time":6.540951465,"remaining_time":18.36267108},
{"learn":[0.4918694249],"iteration":109,"passed_time":6.598149731,"remaining_time":18.29486971},
{"learn":[0.4915679688],"iteration":110,"passed_time":6.65548833,"remaining_time":18.22764371},
{"learn":[0.4913951658],"iteration":111,"passed_time":6.710580766,"remaining_time":18.15451761},
{"learn":[0.4913052457],"iteration":112,"passed_time":6.778033292,"remaining_time":18.11474384},
{"learn":[0.4911234456],"iteration":113,"passed_time":6.84671255,"remaining_time":18.07772349},
{"learn":[0.4909641211],"iteration":114,"passed_time":6.90807473,"remaining_time":18.02106451},
{"learn":[0.4908697274],"iteration":115,"passed_time":6.962859688,"remaining_time":17.94737109},
{"learn":[0.490776462],"iteration":116,"passed_time":7.025861187,"remaining_time":17.89492849},
{"learn":[0.4907723305],"iteration":117,"passed_time":7.047331714,"remaining_time":17.73777558},
{"learn":[0.4904883343],"iteration":118,"passed_time":7.107996739,"remaining_time":17.68039525},
{"learn":[0.4904725391],"iteration":119,"passed_time":7.160061672,"remaining_time":17.60181828},
{"learn":[0.4903354282],"iteration":120,"passed_time":7.221636094,"remaining_time":17.54678522},
{"learn":[0.4901770706],"iteration":121,"passed_time":7.298897887,"remaining_time":17.52932033},
{"learn":[0.4899039584],"iteration":122,"passed_time":7.358320763,"remaining_time":17.46853384},
{"learn":[0.4896701183],"iteration":123,"passed_time":7.41857386,"remaining_time":17.40971769},
{"learn":[0.4892812575],"iteration":124,"passed_time":7.478827622,"remaining_time":17.35088008},
{"learn":[0.4891236096],"iteration":125,"passed_time":7.539645476,"remaining_time":17.29331383},
{"learn":[0.4887805737],"iteration":126,"passed_time":7.595647732,"remaining_time":17.22477596},
{"learn":[0.4886223719],"iteration":127,"passed_time":7.666171781,"remaining_time":17.18899454},
{"learn":[0.4884466373],"iteration":128,"passed_time":7.719777113,"remaining_time":17.11516476},
{"learn":[0.488337689],"iteration":129,"passed_time":7.786297055,"remaining_time":17.06995893},
{"learn":[0.4879722854],"iteration":130,"passed_time":7.843714463,"remaining_time":17.00469395},
{"learn":[0.4877087282],"iteration":131,"passed_time":7.921382244,"remaining_time":16.98296345},
{"learn":[0.4875226009],"iteration":132,"passed_time":7.983583648,"remaining_time":16.92759841},
{"learn":[0.4874220608],"iteration":133,"passed_time":8.04539706,"remaining_time":16.87131772},
{"learn":[0.487346407],"iteration":134,"passed_time":8.11212356,"remaining_time":16.82514516},
{"learn":[0.4872208689],"iteration":135,"passed_time":8.171940469,"remaining_time":16.76449552},
{"learn":[0.4871114655],"iteration":136,"passed_time":8.229258625,"remaining_time":16.69878757},
{"learn":[0.4868628628],"iteration":137,"passed_time":8.285557279,"remaining_time":16.63115483},
{"learn":[0.4867366657],"iteration":138,"passed_time":8.346920212,"remaining_time":16.57374085},
{"learn":[0.4864384916],"iteration":139,"passed_time":8.416106516,"remaining_time":16.5316378},
{"learn":[0.48628103],"iteration":140,"passed_time":8.484626562,"remaining_time":16.48785587},
{"learn":[0.4862377236],"iteration":141,"passed_time":8.54550253,"remaining_time":16.42902951},
{"learn":[0.4861495708],"iteration":142,"passed_time":8.602557792,"remaining_time":16.36290713},
{"learn":[0.48569717],"iteration":143,"passed_time":8.669080043,"remaining_time":16.31472702},
{"learn":[0.4855208677],"iteration":144,"passed_time":8.72892772,"remaining_time":16.25386541},
{"learn":[0.4853518943],"iteration":145,"passed_time":8.79718489,"remaining_time":16.20851189},
{"learn":[0.485164231],"iteration":146,"passed_time":8.857085989,"remaining_time":16.14761255},
{"learn":[0.4850409856],"iteration":147,"passed_time":8.920427534,"remaining_time":16.09293346},
{"learn":[0.4848782177],"iteration":148,"passed_time":8.978832074,"remaining_time":16.02932437},
{"learn":[0.4846206098],"iteration":149,"passed_time":9.042865271,"remaining_time":15.97572864},
{"learn":[0.4844708904],"iteration":150,"passed_time":9.109311666,"remaining_time":15.92621377},
{"learn":[0.4841485818],"iteration":151,"passed_time":9.169346079,"remaining_time":15.8653817},
{"learn":[0.4840360109],"iteration":152,"passed_time":9.237963924,"remaining_time":15.81925848},
{"learn":[0.483655723],"iteration":153,"passed_time":9.300684309,"remaining_time":15.76284808},
{"learn":[0.4833884087],"iteration":154,"passed_time":9.37146844,"remaining_time":15.71988254},
{"learn":[0.4832970415],"iteration":155,"passed_time":9.43068582,"remaining_time":15.65735659},
{"learn":[0.4831558133],"iteration":156,"passed_time":9.501479115,"remaining_time":15.61389562},
{"learn":[0.4831266379],"iteration":157,"passed_time":9.550093451,"remaining_time":15.53401276},
{"learn":[0.4829788017],"iteration":158,"passed_time":9.609642949,"remaining_time":15.47212953},
{"learn":[0.4827565818],"iteration":159,"passed_time":9.674322622,"remaining_time":15.41845168},
{"learn":[0.4825269262],"iteration":160,"passed_time":9.738722045,"remaining_time":15.36419503},
{"learn":[0.4822891505],"iteration":161,"passed_time":9.808051497,"remaining_time":15.31751252},
{"learn":[0.4820626903],"iteration":162,"passed_time":9.878792521,"remaining_time":15.27273445},
{"learn":[0.481875754],"iteration":163,"passed_time":9.946324086,"remaining_time":15.22272772},
{"learn":[0.4814464841],"iteration":164,"passed_time":10.00747258,"remaining_time":15.16283725},
{"learn":[0.4809802686],"iteration":165,"passed_time":10.0640919,"remaining_time":15.09613785},
{"learn":[0.4809639678],"iteration":166,"passed_time":10.10579069,"remaining_time":15.00740175},
{"learn":[0.4808893594],"iteration":167,"passed_time":10.16643504,"remaining_time":14.94708008},
{"learn":[0.4807835999],"iteration":168,"passed_time":10.23214166,"remaining_time":14.89412337},
{"learn":[0.4804760493],"iteration":169,"passed_time":10.2970321,"remaining_time":14.83984038},
{"learn":[0.4803195454],"iteration":170,"passed_time":10.36418495,"remaining_time":14.78866156},
{"learn":[0.4802398418],"iteration":171,"passed_time":10.42341567,"remaining_time":14.7261047},
{"learn":[0.4801681116],"iteration":172,"passed_time":10.48178798,"remaining_time":14.6623855},
{"learn":[0.4801184364],"iteration":173,"passed_time":10.54202094,"remaining_time":14.60130487},
{"learn":[0.4800603231],"iteration":174,"passed_time":10.61006139,"remaining_time":14.55094133},
{"learn":[0.4797703963],"iteration":175,"passed_time":10.66908417,"remaining_time":14.48813134},
{"learn":[0.4795747755],"iteration":176,"passed_time":10.72729467,"remaining_time":14.42427193},
{"learn":[0.4794238701],"iteration":177,"passed_time":10.78372277,"remaining_time":14.35810279},
{"learn":[0.4790630061],"iteration":178,"passed_time":10.84844486,"remaining_time":14.30297758},
{"learn":[0.4789104653],"iteration":179,"passed_time":10.90445856,"remaining_time":14.23637646},
{"learn":[0.4786725525],"iteration":180,"passed_time":10.9618281,"remaining_time":14.17164517},
{"learn":[0.4784780492],"iteration":181,"passed_time":11.01995801,"remaining_time":14.10796822},
{"learn":[0.4781213171],"iteration":182,"passed_time":11.08796045,"remaining_time":14.05686789},
{"learn":[0.4780753778],"iteration":183,"passed_time":11.15094537,"remaining_time":13.99928468},
{"learn":[0.4779073978],"iteration":184,"passed_time":11.21154488,"remaining_time":13.93867741},
{"learn":[0.4778280782],"iteration":185,"passed_time":11.27891636,"remaining_time":13.88640778},
{"learn":[0.4778023823],"iteration":186,"passed_time":11.34383717,"remaining_time":13.83098864},
{"learn":[0.4776089157],"iteration":187,"passed_time":11.40814775,"remaining_time":13.77473159},
{"learn":[0.4773883025],"iteration":188,"passed_time":11.47919698,"remaining_time":13.72644718},
{"learn":[0.4770551383],"iteration":189,"passed_time":11.54332748,"remaining_time":13.66972991},
{"learn":[0.4769940512],"iteration":190,"passed_time":11.60585937,"remaining_time":13.6110602},
{"learn":[0.4769658407],"iteration":191,"passed_time":11.66999143,"remaining_time":13.5542088},
{"learn":[0.476804005],"iteration":192,"passed_time":11.72911522,"remaining_time":13.49152113},
{"learn":[0.4767059343],"iteration":193,"passed_time":11.78890707,"remaining_time":13.42963124},
{"learn":[0.4762382412],"iteration":194,"passed_time":11.85834199,"remaining_time":13.37864224},
{"learn":[0.4760672068],"iteration":195,"passed_time":11.92430855,"remaining_time":13.32358966},
{"learn":[0.476000429],"iteration":196,"passed_time":11.98112382,"remaining_time":13.25829946},
{"learn":[0.4759613742],"iteration":197,"passed_time":12.04506359,"remaining_time":13.20090303},
{"learn":[0.4757025314],"iteration":198,"passed_time":12.10565326,"remaining_time":13.13980454},
{"learn":[0.4753922242],"iteration":199,"passed_time":12.16246093,"remaining_time":13.0746455},
{"learn":[0.4753319548],"iteration":200,"passed_time":12.22581431,"remaining_time":13.01653862},
{"learn":[0.4751751966],"iteration":201,"passed_time":12.28403535,"remaining_time":12.95296797},
{"learn":[0.4749975664],"iteration":202,"passed_time":12.34249892,"remaining_time":12.88970331},
{"learn":[0.4747747729],"iteration":203,"passed_time":12.40416491,"remaining_time":12.82979801},
{"learn":[0.4743563011],"iteration":204,"passed_time":12.46335658,"remaining_time":12.76734089},
{"learn":[0.4743019319],"iteration":205,"passed_time":12.52379701,"remaining_time":12.70618241},
{"learn":[0.4740135784],"iteration":206,"passed_time":12.58408643,"remaining_time":12.64487912},
{"learn":[0.4737432185],"iteration":207,"passed_time":12.64199273,"remaining_time":12.58121392},
{"learn":[0.4736010477],"iteration":208,"passed_time":12.70142839,"remaining_time":12.51911124},
{"learn":[0.4733597997],"iteration":209,"passed_time":12.76202521,"remaining_time":12.45816746},
{"learn":[0.4732546566],"iteration":210,"passed_time":12.81944882,"remaining_time":12.39415905},
{"learn":[0.4729008662],"iteration":211,"passed_time":12.88135175,"remaining_time":12.33450191},
{"learn":[0.4726514505],"iteration":212,"passed_time":12.94202461,"remaining_time":12.27365715},
{"learn":[0.4722849278],"iteration":213,"passed_time":13.00125617,"remaining_time":12.21146024},
{"learn":[0.4718258193],"iteration":214,"passed_time":13.05743602,"remaining_time":12.14645211},
{"learn":[0.4717994334],"iteration":215,"passed_time":13.11543304,"remaining_time":12.08319989},
{"learn":[0.471692804],"iteration":216,"passed_time":13.17230991,"remaining_time":12.01897402},
{"learn":[0.4715330799],"iteration":217,"passed_time":13.23327648,"remaining_time":11.95851132},
{"learn":[0.4714855254],"iteration":218,"passed_time":13.30295317,"remaining_time":11.90583936},
{"learn":[0.4711611303],"iteration":219,"passed_time":13.36681797,"remaining_time":11.84786138},
{"learn":[0.4710241581],"iteration":220,"passed_time":13.43034292,"remaining_time":11.78953179},
{"learn":[0.4708128298],"iteration":221,"passed_time":13.49002439,"remaining_time":11.727814},
{"learn":[0.4706143972],"iteration":222,"passed_time":13.55207155,"remaining_time":11.66815129},
{"learn":[0.4704073232],"iteration":223,"passed_time":13.61681148,"remaining_time":11.61076336},
{"learn":[0.470221903],"iteration":224,"passed_time":13.67452726,"remaining_time":11.54737858},
{"learn":[0.4701641726],"iteration":225,"passed_time":13.73957216,"remaining_time":11.49017318},
{"learn":[0.4700776962],"iteration":226,"passed_time":13.81053228,"remaining_time":11.43779766},
{"learn":[0.4700215117],"iteration":227,"passed_time":13.87604824,"remaining_time":11.38079395},
{"learn":[0.469956858],"iteration":228,"passed_time":13.93388314,"remaining_time":11.31747713},
{"learn":[0.4697496081],"iteration":229,"passed_time":13.99378491,"remaining_time":11.25587047},
{"learn":[0.4695901244],"iteration":230,"passed_time":14.05560055,"remaining_time":11.19580303},
{"learn":[0.4693540243],"iteration":231,"passed_time":14.1259223,"remaining_time":11.14243009},
{"learn":[0.4692913224],"iteration":232,"passed_time":14.19193004,"remaining_time":11.08554192},
{"learn":[0.4691761171],"iteration":233,"passed_time":14.25584663,"remaining_time":11.02695829},
{"learn":[0.4689280722],"iteration":234,"passed_time":14.32151959,"remaining_time":10.96967458},
{"learn":[0.4688973903],"iteration":235,"passed_time":14.3817417,"remaining_time":10.90818544},
{"learn":[0.468796441],"iteration":236,"passed_time":14.44496796,"remaining_time":10.84896328},
{"learn":[0.4687505924],"iteration":237,"passed_time":14.51458553,"remaining_time":10.79446066},
{"learn":[0.4686225884],"iteration":238,"passed_time":14.57280744,"remaining_time":10.73143979},
{"learn":[0.4683582294],"iteration":239,"passed_time":14.63884468,"remaining_time":10.67415758},
{"learn":[0.4682829124],"iteration":240,"passed_time":14.69649949,"remaining_time":10.61075067},
{"learn":[0.4681295924],"iteration":241,"passed_time":14.75365384,"remaining_time":10.54703353},
{"learn":[0.4677150797],"iteration":242,"passed_time":14.80912984,"remaining_time":10.48218244},
{"learn":[0.4676323802],"iteration":243,"passed_time":14.87251079,"remaining_time":10.42294814},
{"learn":[0.4675387011],"iteration":244,"passed_time":14.93998322,"remaining_time":10.36651897},
{"learn":[0.4673229814],"iteration":245,"passed_time":15.0058848,"remaining_time":10.30892086},
{"learn":[0.4670917515],"iteration":246,"passed_time":15.06770673,"remaining_time":10.24848069},
{"learn":[0.4669803688],"iteration":247,"passed_time":15.12879094,"remaining_time":10.18753261},
{"learn":[0.4668527962],"iteration":248,"passed_time":15.20287654,"remaining_time":10.13525103},
{"learn":[0.4667760296],"iteration":249,"passed_time":15.2819655,"remaining_time":10.08609723},
{"learn":[0.4667089469],"iteration":250,"passed_time":15.34431251,"remaining_time":10.02576594},
{"learn":[0.4665976003],"iteration":251,"passed_time":15.41064929,"remaining_time":9.967999343},
{"learn":[0.4663753945],"iteration":252,"passed_time":15.48750258,"remaining_time":9.916898888},
{"learn":[0.4663144837],"iteration":253,"passed_time":15.55383288,"remaining_time":9.858925566},
{"learn":[0.466279644],"iteration":254,"passed_time":15.60884166,"remaining_time":9.793783003},
{"learn":[0.4660764846],"iteration":255,"passed_time":15.66645937,"remaining_time":9.73034},
{"learn":[0.4658640179],"iteration":256,"passed_time":15.72335466,"remaining_time":9.666498193},
{"learn":[0.4657333239],"iteration":257,"passed_time":15.78273948,"remaining_time":9.604225188},
{"learn":[0.4654706765],"iteration":258,"passed_time":15.84146623,"remaining_time":9.541578114},
{"learn":[0.4652714572],"iteration":259,"passed_time":15.89885287,"remaining_time":9.47816229},
{"learn":[0.4647623453],"iteration":260,"passed_time":15.96495783,"remaining_time":9.419936806},
{"learn":[0.4647019099],"iteration":261,"passed_time":16.02224079,"remaining_time":9.356499395},
{"learn":[0.4645697214],"iteration":262,"passed_time":16.07893704,"remaining_time":9.292769696},
{"learn":[0.4645159326],"iteration":263,"passed_time":16.1454352,"remaining_time":9.234699681},
{"learn":[0.4643228501],"iteration":264,"passed_time":16.20593845,"remaining_time":9.173172706},
{"learn":[0.4641888964],"iteration":265,"passed_time":16.27264975,"remaining_time":9.115130876},
{"learn":[0.4639947248],"iteration":266,"passed_time":16.33035119,"remaining_time":9.052029874},
{"learn":[0.4636515951],"iteration":267,"passed_time":16.39558494,"remaining_time":8.993100696},
{"learn":[0.4635426428],"iteration":268,"passed_time":16.478906,"remaining_time":8.943941545},
{"learn":[0.4632904501],"iteration":269,"passed_time":16.53710874,"remaining_time":8.881039879},
{"learn":[0.463026547],"iteration":270,"passed_time":16.59748664,"remaining_time":8.819328693},
{"learn":[0.4628238525],"iteration":271,"passed_time":16.66143308,"remaining_time":8.75950342},
{"learn":[0.462715252],"iteration":272,"passed_time":16.71929023,"remaining_time":8.69648063},
{"learn":[0.4624684786],"iteration":273,"passed_time":16.78252768,"remaining_time":8.636264245},
{"learn":[0.4622809039],"iteration":274,"passed_time":16.84357377,"remaining_time":8.574910281},
{"learn":[0.4622193073],"iteration":275,"passed_time":16.90890697,"remaining_time":8.51571764},
{"learn":[0.4620157857],"iteration":276,"passed_time":16.96700041,"remaining_time":8.452873852},
{"learn":[0.4619555712],"iteration":277,"passed_time":17.0327386,"remaining_time":8.393831612},
{"learn":[0.4617601394],"iteration":278,"passed_time":17.08956689,"remaining_time":8.330398199},
{"learn":[0.4616636005],"iteration":279,"passed_time":17.15363942,"remaining_time":8.27050472},
{"learn":[0.4615456198],"iteration":280,"passed_time":17.21034764,"remaining_time":8.207069694},
{"learn":[0.4613125842],"iteration":281,"passed_time":17.27052835,"remaining_time":8.145320109},
{"learn":[0.4608871107],"iteration":282,"passed_time":17.3358296,"remaining_time":8.085969988},
{"learn":[0.4605165163],"iteration":283,"passed_time":17.39277985,"remaining_time":8.022725915},
{"learn":[0.4603571126],"iteration":284,"passed_time":17.44943142,"remaining_time":7.959389769},
{"learn":[0.4600452439],"iteration":285,"passed_time":17.50814449,"remaining_time":7.897030205},
{"learn":[0.4599096671],"iteration":286,"passed_time":17.57476115,"remaining_time":7.838220999},
{"learn":[0.4598805957],"iteration":287,"passed_time":17.63334489,"remaining_time":7.775815281},
{"learn":[0.4596680464],"iteration":288,"passed_time":17.70610965,"remaining_time":7.719618739},
{"learn":[0.459658003],"iteration":289,"passed_time":17.76660816,"remaining_time":7.65802076},
{"learn":[0.4594867372],"iteration":290,"passed_time":17.83375021,"remaining_time":7.599261259},
{"learn":[0.4593943369],"iteration":291,"passed_time":17.89107932,"remaining_time":7.53631081},
{"learn":[0.4591709671],"iteration":292,"passed_time":17.95543384,"remaining_time":7.476323986},
{"learn":[0.4588555156],"iteration":293,"passed_time":18.0236704,"remaining_time":7.417905163},
{"learn":[0.4587934018],"iteration":294,"passed_time":18.08271258,"remaining_time":7.355679694},
{"learn":[0.4586781033],"iteration":295,"passed_time":18.14045994,"remaining_time":7.292955179},
{"learn":[0.4586421733],"iteration":296,"passed_time":18.19808359,"remaining_time":7.230215029},
{"learn":[0.4584345422],"iteration":297,"passed_time":18.26157793,"remaining_time":7.169814153},
{"learn":[0.4583708565],"iteration":298,"passed_time":18.32437344,"remaining_time":7.109121469},
{"learn":[0.4581264342],"iteration":299,"passed_time":18.38499863,"remaining_time":7.047582808},
{"learn":[0.4578944123],"iteration":300,"passed_time":18.4442086,"remaining_time":6.985514219},
{"learn":[0.4576790728],"iteration":301,"passed_time":18.50753497,"remaining_time":6.925004807},
{"learn":[0.457469692],"iteration":302,"passed_time":18.5700544,"remaining_time":6.864178526},
{"learn":[0.457440747],"iteration":303,"passed_time":18.63094201,"remaining_time":6.802745272},
{"learn":[0.4573751629],"iteration":304,"passed_time":18.69749791,"remaining_time":6.743359902},
{"learn":[0.4573338693],"iteration":305,"passed_time":18.77283758,"remaining_time":6.687056522},
{"learn":[0.4572623268],"iteration":306,"passed_time":18.84681896,"remaining_time":6.630151295},
{"learn":[0.4572498695],"iteration":307,"passed_time":18.90356019,"remaining_time":6.567145909},
{"learn":[0.4571779377],"iteration":308,"passed_time":18.96075683,"remaining_time":6.504337294},
{"learn":[0.4570435698],"iteration":309,"passed_time":19.02468056,"remaining_time":6.443843417},
{"learn":[0.456792601],"iteration":310,"passed_time":19.09238964,"remaining_time":6.38459332},
{"learn":[0.4566485778],"iteration":311,"passed_time":19.15276656,"remaining_time":6.322868449},
{"learn":[0.4565545275],"iteration":312,"passed_time":19.21854395,"remaining_time":6.262912086},
{"learn":[0.4564639159],"iteration":313,"passed_time":19.28583135,"remaining_time":6.203404351},
{"learn":[0.4564530642],"iteration":314,"passed_time":19.34549243,"remaining_time":6.141426169},
{"learn":[0.4560630391],"iteration":315,"passed_time":19.40319208,"remaining_time":6.078848151},
{"learn":[0.4558729265],"iteration":316,"passed_time":19.46042824,"remaining_time":6.016157627},
{"learn":[0.4556590073],"iteration":317,"passed_time":19.51687983,"remaining_time":5.953262086},
{"learn":[0.4556094999],"iteration":318,"passed_time":19.57697228,"remaining_time":5.891502629},
{"learn":[0.4552417413],"iteration":319,"passed_time":19.64475453,"remaining_time":5.8320365},
{"learn":[0.4551083093],"iteration":320,"passed_time":19.70189289,"remaining_time":5.769401655},
{"learn":[0.455033916],"iteration":321,"passed_time":19.76181322,"remaining_time":5.707604439},
{"learn":[0.4549008876],"iteration":322,"passed_time":19.81761908,"remaining_time":5.644646919},
{"learn":[0.4547970362],"iteration":323,"passed_time":19.88476991,"remaining_time":5.584919943},
{"learn":[0.4547150247],"iteration":324,"passed_time":19.94974462,"remaining_time":5.524544663},
{"learn":[0.4545640544],"iteration":325,"passed_time":20.01221137,"remaining_time":5.463456479},
{"learn":[0.4545521675],"iteration":326,"passed_time":20.07273675,"remaining_time":5.401837414},
{"learn":[0.4543664687],"iteration":327,"passed_time":20.12922239,"remaining_time":5.339153499},
{"learn":[0.4540795311],"iteration":328,"passed_time":20.19172501,"remaining_time":5.278080094},
{"learn":[0.453890663],"iteration":329,"passed_time":20.25515296,"remaining_time":5.217236367},
{"learn":[0.4537480846],"iteration":330,"passed_time":20.31870334,"remaining_time":5.156408099},
{"learn":[0.4536620203],"iteration":331,"passed_time":20.3827999,"remaining_time":5.095699976},
{"learn":[0.453533302],"iteration":332,"passed_time":20.4454596,"remaining_time":5.03461768},
{"learn":[0.4535080249],"iteration":333,"passed_time":20.50714809,"remaining_time":4.973290406},
{"learn":[0.4532595537],"iteration":334,"passed_time":20.56828987,"remaining_time":4.911830417},
{"learn":[0.4532383714],"iteration":335,"passed_time":20.63234185,"remaining_time":4.851056566},
{"learn":[0.4531558127],"iteration":336,"passed_time":20.68778868,"remaining_time":4.788271563},
{"learn":[0.4529261758],"iteration":337,"passed_time":20.74837583,"remaining_time":4.726701003},
{"learn":[0.4527978866],"iteration":338,"passed_time":20.81032387,"remaining_time":4.665441339},
{"learn":[0.4527008898],"iteration":339,"passed_time":20.88690001,"remaining_time":4.607404413},
{"learn":[0.4525216518],"iteration":340,"passed_time":20.94908349,"remaining_time":4.546135421},
{"learn":[0.4521776904],"iteration":341,"passed_time":21.00643866,"remaining_time":4.483830475},
{"learn":[0.4520997115],"iteration":342,"passed_time":21.06877351,"remaining_time":4.422599688},
{"learn":[0.4519522065],"iteration":343,"passed_time":21.12898058,"remaining_time":4.360923318},
{"learn":[0.451721608],"iteration":344,"passed_time":21.19050661,"remaining_time":4.29952308},
{"learn":[0.4515519555],"iteration":345,"passed_time":21.24832403,"remaining_time":4.237382537},
{"learn":[0.4514178623],"iteration":346,"passed_time":21.31189345,"remaining_time":4.176394106},
{"learn":[0.4511691291],"iteration":347,"passed_time":21.37487862,"remaining_time":4.115278355},
{"learn":[0.4509338141],"iteration":348,"passed_time":21.43409154,"remaining_time":4.053438514},
{"learn":[0.4507928266],"iteration":349,"passed_time":21.49327289,"remaining_time":3.991607822},
{"learn":[0.4506817634],"iteration":350,"passed_time":21.55043479,"remaining_time":3.929424008},
{"learn":[0.4505034477],"iteration":351,"passed_time":21.61647811,"remaining_time":3.868858298},
{"learn":[0.4504925161],"iteration":352,"passed_time":21.68011474,"remaining_time":3.807838849},
{"learn":[0.4501399848],"iteration":353,"passed_time":21.73952691,"remaining_time":3.746076671},
{"learn":[0.4501238823],"iteration":354,"passed_time":21.80270963,"remaining_time":3.684965007},
{"learn":[0.4499051614],"iteration":355,"passed_time":21.86453338,"remaining_time":3.623616487},
{"learn":[0.4496509565],"iteration":356,"passed_time":21.93261268,"remaining_time":3.563281612},
{"learn":[0.4495419774],"iteration":357,"passed_time":21.995487,"remaining_time":3.502074746},
{"learn":[0.4492849015],"iteration":358,"passed_time":22.07424615,"remaining_time":3.443336446},
{"learn":[0.449209146],"iteration":359,"passed_time":22.13223726,"remaining_time":3.381314026},
{"learn":[0.4490300111],"iteration":360,"passed_time":22.19496303,"remaining_time":3.320022171},
{"learn":[0.4489153249],"iteration":361,"passed_time":22.26202213,"remaining_time":3.259356831},
{"learn":[0.4488904966],"iteration":362,"passed_time":22.32508949,"remaining_time":3.198084446},
{"learn":[0.4488334184],"iteration":363,"passed_time":22.38566277,"remaining_time":3.136452751},
{"learn":[0.448512845],"iteration":364,"passed_time":22.44811004,"remaining_time":3.075083568},
{"learn":[0.4485116598],"iteration":365,"passed_time":22.51341254,"remaining_time":3.014090749},
{"learn":[0.4482371467],"iteration":366,"passed_time":22.57362094,"remaining_time":2.952408188},
{"learn":[0.4482069329],"iteration":367,"passed_time":22.64090225,"remaining_time":2.891636972},
{"learn":[0.4481829273],"iteration":368,"passed_time":22.69885085,"remaining_time":2.829667044},
{"learn":[0.4481028184],"iteration":369,"passed_time":22.77518141,"remaining_time":2.769954495},
{"learn":[0.4478632811],"iteration":370,"passed_time":22.83873676,"remaining_time":2.708637244},
{"learn":[0.4476222874],"iteration":371,"passed_time":22.90055517,"remaining_time":2.647107184},
{"learn":[0.4473578914],"iteration":372,"passed_time":22.96983243,"remaining_time":2.586415448},
{"learn":[0.4472910206],"iteration":373,"passed_time":23.03875775,"remaining_time":2.525639219},
{"learn":[0.4472631811],"iteration":374,"passed_time":23.10354648,"remaining_time":2.464378292},
{"learn":[0.4470753082],"iteration":375,"passed_time":23.16937497,"remaining_time":2.403206446},
{"learn":[0.4469612025],"iteration":376,"passed_time":23.23415531,"remaining_time":2.341904248},
{"learn":[0.4467557475],"iteration":377,"passed_time":23.2939705,"remaining_time":2.280097642},
{"learn":[0.4466577932],"iteration":378,"passed_time":23.35683795,"remaining_time":2.218591467},
{"learn":[0.4466040554],"iteration":379,"passed_time":23.41995759,"remaining_time":2.157101357},
{"learn":[0.4464081449],"iteration":380,"passed_time":23.48911309,"remaining_time":2.096141325},
{"learn":[0.4462022949],"iteration":381,"passed_time":23.55261962,"remaining_time":2.034650386},
{"learn":[0.4461265071],"iteration":382,"passed_time":23.6156425,"remaining_time":1.973108512},
{"learn":[0.4460231174],"iteration":383,"passed_time":23.67792911,"remaining_time":1.911499486},
{"learn":[0.445895878],"iteration":384,"passed_time":23.742278,"remaining_time":1.850047637},
{"learn":[0.4457691138],"iteration":385,"passed_time":23.80239543,"remaining_time":1.788262869},
{"learn":[0.445750917],"iteration":386,"passed_time":23.86350654,"remaining_time":1.726558613},
{"learn":[0.4456166713],"iteration":387,"passed_time":23.93205827,"remaining_time":1.665375189},
{"learn":[0.4454197263],"iteration":388,"passed_time":24.0015899,"remaining_time":1.604219376},
{"learn":[0.4452273429],"iteration":389,"passed_time":24.06231985,"remaining_time":1.542456401},
{"learn":[0.4450243775],"iteration":390,"passed_time":24.12018082,"remaining_time":1.480522608},
{"learn":[0.4448882148],"iteration":391,"passed_time":24.1838886,"remaining_time":1.418952648},
{"learn":[0.4448770201],"iteration":392,"passed_time":24.24094877,"remaining_time":1.356999677},
{"learn":[0.4446739296],"iteration":393,"passed_time":24.30058944,"remaining_time":1.295209082},
{"learn":[0.4445816111],"iteration":394,"passed_time":24.370538,"remaining_time":1.233951291},
{"learn":[0.4445380438],"iteration":395,"passed_time":24.43174003,"remaining_time":1.172229951},
{"learn":[0.444264876],"iteration":396,"passed_time":24.48983762,"remaining_time":1.110370472},
{"learn":[0.4441191134],"iteration":397,"passed_time":24.54839477,"remaining_time":1.048549526},
{"learn":[0.4439669346],"iteration":398,"passed_time":24.60363703,"remaining_time":0.9866120113},
{"learn":[0.4438540172],"iteration":399,"passed_time":24.66856951,"remaining_time":0.9250713565},
{"learn":[0.4438188812],"iteration":400,"passed_time":24.72733886,"remaining_time":0.8632986135},
{"learn":[0.4437679217],"iteration":401,"passed_time":24.78651662,"remaining_time":0.80155402},
{"learn":[0.4436748815],"iteration":402,"passed_time":24.84700405,"remaining_time":0.7398611627},
{"learn":[0.443510406],"iteration":403,"passed_time":24.90768885,"remaining_time":0.678179647},
{"learn":[0.4433677232],"iteration":404,"passed_time":24.9680901,"remaining_time":0.6164960518},
{"learn":[0.4433326177],"iteration":405,"passed_time":25.03259162,"remaining_time":0.5549096664},
{"learn":[0.4430970916],"iteration":406,"passed_time":25.09678363,"remaining_time":0.4933028723},
{"learn":[0.4429164785],"iteration":407,"passed_time":25.15698887,"remaining_time":0.4316150051},
{"learn":[0.4427770331],"iteration":408,"passed_time":25.21433921,"remaining_time":0.3698925067},
{"learn":[0.4426777256],"iteration":409,"passed_time":25.27700478,"remaining_time":0.3082561558},
{"learn":[0.4425924355],"iteration":410,"passed_time":25.34062983,"remaining_time":0.2466241346},
{"learn":[0.4425839891],"iteration":411,"passed_time":25.41441011,"remaining_time":0.1850563843},
{"learn":[0.4424412498],"iteration":412,"passed_time":25.47748263,"remaining_time":0.1233776399},
{"learn":[0.4422406162],"iteration":413,"passed_time":25.55973812,"remaining_time":0.06173849787},
{"learn":[0.4422341493],"iteration":414,"passed_time":25.62450581,"remaining_time":0}
]}